macos_window_info/__init__.py
macos_window_info/main.py
macos_window_info-0.1.0.dist-info/LICENSE
macos_window_info-0.1.0.dist-info/METADATA
macos_window_info-0.1.0.dist-info/WHEEL
macos_window_info-0.1.0.dist-info/entry_points.txt
macos_window_info-0.1.0.dist-info/RECORD
