Metadata-Version: 2.3
Name: macos-window-info
Version: 0.1.0
Summary: A Python tool to find the process ID (PID) of a macOS window by its title or other attributes
License: MIT
Keywords: macos,window,pid,process,quartz
Author: Bernardo Martins
Author-email: bsamartins@gmail.com
Requires-Python: >=3.13
Classifier: Development Status :: 3 - Alpha
Classifier: Intended Audience :: Developers
Classifier: License :: OSI Approved :: MIT License
Classifier: Operating System :: MacOS
Classifier: Programming Language :: Python :: 3
Classifier: Programming Language :: Python :: 3.13
Classifier: Topic :: Software Development :: Libraries :: Python Modules
Classifier: Topic :: System :: Monitoring
Provides-Extra: dev
Requires-Dist: black (>=23.0.0) ; extra == "dev"
Requires-Dist: flake8 (>=6.0.0) ; extra == "dev"
Requires-Dist: isort (>=5.12.0) ; extra == "dev"
Requires-Dist: mypy (>=1.5.0) ; extra == "dev"
Requires-Dist: pyobjc-framework-quartz (>=11.1,<12.0)
Requires-Dist: pytest (>=7.4.0) ; extra == "dev"
Requires-Dist: pytest-cov (>=4.1.0) ; extra == "dev"
Project-URL: Homepage, https://github.com/bsamartins/macos-window-info
Project-URL: Issues, https://github.com/bsamartins/macos-window-info/issues
Project-URL: Repository, https://github.com/bsamartins/macos-window-info
